startup.v
// This is the file where the FSM design would be created 

module startup_fsm(
    input reset_all, //Active low 
    input i_clk,
    input ready_serial, // This would come from the serial_comm module showing data has been transferred 
    output reg o_ready,
    output reg o_resetb1,  //Active low for amp1
    output reg o_resetb2, //Active low for amp2
    output reg o_resetbvco //Active low for VCO
);

// We need to handle the clock domain crossing part. 
// Ready serial comes from i_sclk clock and now we have a high freq i_clk
// This needs to be taken care of using a synchornizer 

    reg ready_sync1, ready_sync2;

    always @(posedge i_clk) begin
        if (!reset_all) begin
            ready_sync1 <= 0;
            ready_sync2 <= 0;
        end else begin
            ready_sync1 <= ready_serial;
            ready_sync2 <= ready_sync1;
        end
    end

    // Now we can start with the actual FSM now that CDC is handeled 
    
    // State encoding. We have 8 states (2 of these are similar so they might be reducable)
    // I am doing a Moore implementation now, but a Mealey can be done to save the last state
    // But still we would need 3 flip flops even in moore
    parameter RST=3'b000; //reset_all
    parameter WAIT_SERIAL =3'b001; //wait_serial
    parameter WAIT_2CYC = 3'b010;
    parameter SET_VCO = 3'b011;
    parameter WAIT_10A = 3'b100;
    parameter SET_AMPS = 3'b101;
    parameter WAIT_10B = 3'b110;
    parameter DONE = 3'b111;

    //Registers for FSM
    reg [2:0] current_state, next_state;
    reg [3:0] counter; // counter for the delay blocks

    // Sequential logic to update states

    always @(posedge i_clk) begin //The PS does not mention a reset type. Assuming synchronous reset for simplicity

    if(!reset_all) begin 
        counter <= 0;
        current_state <= RST; //Since active low, this handles reset here so we wont have to do it again and again in each state
    end

    else begin 
        current_state <= next_state;
        if (current_state != next_state) begin //during transitions
            counter <= 0;
        end

        else counter <= counter + 1; //increment counter to find delay
    end

    end

    //Combinational logic that just sets the next state and all corresponding outputs

    always @(*) begin
        // default outputs
        o_ready = 0;
        o_resetb1 = 0;
        o_resetb2 = 0;
        o_resetbvco = 0;

        next_state = current_state;
        case(current_state)
            RST: begin
                // Reset all backend outputs and other regs
                o_ready = 0;
                o_resetb1 = 0;
                o_resetb2 = 0;
                o_resetbvco = 0;

                if(reset_all) next_state = WAIT_SERIAL;

            end

            WAIT_SERIAL: begin 
                // serial comm would happen and set the ready-serial high, which after CDC synchronization has become ready_sync2
                if (ready_sync2) next_state = WAIT_2CYC;

            end

            WAIT_2CYC: begin
                if (counter == 2) next_state = SET_VCO; //counter set in the sequential block above
            end

            SET_VCO: begin 
                o_resetbvco = 1;
                next_state = WAIT_10A;

            end

            WAIT_10A: begin
                o_resetbvco = 1;
                if (counter == 10) next_state = SET_AMPS;
            end

            SET_AMPS: begin 
                o_resetbvco = 1;
                o_resetb1 = 1;
                o_resetb2 = 1;
                next_state = WAIT_10B;
            end

            WAIT_10B: begin 
                o_resetbvco = 1;
                o_resetb1 = 1;
                o_resetb2 = 1;
                if (counter == 10) next_state = DONE;
            end

            DONE: begin
                o_resetbvco = 1;
                o_resetb1 = 1;
                o_resetb2 = 1; // Hold all values
                o_ready = 1; // Chip is ready!
            end

            default: next_state = RST; //for synthesizability


        endcase

    end

endmodule

serial.v
module serial_comm (
    input i_sclk,
    input i_sdin,
    input i_reset, // this will be an active low synchronous reset
    output reg [1:0] o_gainA1,
    output reg [2:0] o_gainA2,
    output reg ready_serial
);

reg [4:0] d; 
reg [2:0] count;
reg stop, final_stop;

always @(posedge i_sclk or negedge i_reset) begin //asynch reset

    if(!i_reset) begin 
        d <= 0;
        ready_serial <= 0;
        o_gainA1 <= 0;
        o_gainA2 <= 0;
        count <= 0;
        stop <= 0;
        final_stop <= 0;
    end

    else if (stop & !(final_stop)) begin 
        // I am updating the gains one clk edge after the 5th clk edge 
        // this is done solely for ease of design. 
        o_gainA1[0] <= d[0];
        o_gainA1[1] <= d[1];
        o_gainA2[0] <= d[2];
        o_gainA2[1] <= d[3];
        o_gainA2[2] <= d[4];
        ready_serial <= 1;
        final_stop <= 1; // this will now ensure that gains are assigned only once
    end

    else if (!stop) begin 

        // Sample the input
        d[count] <= i_sdin;

        count <= count + 1;
        if(count == (3'b100)) stop <= 1;

    end

end

endmodule

main.v
// This is the main file where we will connect all blocks

/*
EE619 project 1 
Submitted by - Samarth Sharma Bhardwaj (230903)
*/

module backend(
    input i_resetbAll, i_clk, i_sclk, i_sdin, i_vco_clk,
    output o_resetb1, o_resetb2, o_resetbvco, o_ready,
    output [1:0] o_gainA1,
    output [2:0] o_gainA2
);

    wire ready_serial;

    // Instantiate the modules

    serial_comm ser(
    .i_sclk(i_sclk),
    .i_sdin(i_sdin),
    .i_reset(i_resetbAll),
    .o_gainA1(o_gainA1),
    .o_gainA2(o_gainA2),
    .ready_serial(ready_serial)
    );

    startup_fsm fsm(
        .reset_all(i_resetbAll),
        .i_clk(i_clk),
        .ready_serial(ready_serial),
        .o_ready(o_ready),
        .o_resetb1(o_resetb1),
        .o_resetb2(o_resetb2),
        .o_resetbvco(o_resetbvco)
    );

endmodule

tb.v
// Testbench for EE619 Project 1 - Backend Module (v4 - FINAL)
// Design verified correct via diagnostic testbench.
// All previous failures were testbench timing issues.
// Fix: wait_and_check now waits for full sequence completion before checking.

`timescale 1ns/1ps

module tb_backend;

    // -------------------------
    // DUT Signals
    // -------------------------
    reg i_resetbAll;
    reg i_clk;
    reg i_sclk;
    reg i_sdin;
    reg i_vco_clk;

    wire o_resetb1, o_resetb2, o_resetbvco, o_ready;
    wire [1:0] o_gainA1;
    wire [2:0] o_gainA2;

    // -------------------------
    // DUT Instantiation
    // -------------------------
    backend dut (
        .i_resetbAll(i_resetbAll),
        .i_clk(i_clk),
        .i_sclk(i_sclk),
        .i_sdin(i_sdin),
        .i_vco_clk(i_vco_clk),
        .o_resetb1(o_resetb1),
        .o_resetb2(o_resetb2),
        .o_resetbvco(o_resetbvco),
        .o_ready(o_ready),
        .o_gainA1(o_gainA1),
        .o_gainA2(o_gainA2)
    );

    // -------------------------
    // i_clk: 200 MHz, period = 5ns
    // -------------------------
    initial i_clk = 0;
    always #2.5 i_clk = ~i_clk;

    // -------------------------
    // Task: Apply and hold reset
    // Toggles i_sclk during reset to flush serial_comm's synchronous reset
    // (harmless for async reset version too)
    // Ends with i_resetbAll=0, i_sclk=1 (idle high)
    // Caller must release i_resetbAll=1
    // -------------------------
    task do_reset;
        integer i;
        begin
            i_resetbAll = 0;
            i_sdin      = 0;
            i_sclk      = 1;
            for (i = 0; i < 6; i = i + 1) begin
                #100; i_sclk = 0;
                #100; i_sclk = 1;
            end
            repeat(3) @(posedge i_clk);
            #1;
        end
    endtask

    // -------------------------
    // Task: Send 5 serial bits
    // data[0]=d0 ... data[4]=d4
    // gainA1={d1,d0}, gainA2={d4,d3,d2}
    // i_sclk must be idle HIGH before calling
    // Note: serial_comm needs one EXTRA sclk edge after the 5th
    // to assign gains (stop fires on edge 5, gains assigned on edge 6)
    // This task sends 6 edges total to ensure gains are latched.
    // -------------------------
    task send_serial;
        input [4:0] data;
        integer i;
        begin
            // Send 5 data bits
            for (i = 0; i < 5; i = i + 1) begin
                #100; i_sclk = 0;
                #10;  i_sdin = data[i];
                #90;  i_sclk = 1;
            end
            // 6th edge: triggers gain assignment in serial_comm
            // (stop=1 from edge 5, so else-if(stop & !final_stop) fires here)
            #100; i_sclk = 0;
            #100; i_sclk = 1;
            // Return to idle
            i_sdin = 0;
            #100;
        end
    endtask

    // -------------------------
    // Task: Wait for full sequence and verify
    //
    // From diagnostic output, total sequence after ready_serial goes high:
    //   CDC sync:  1 i_clk cycle
    //   WAIT_2CYC: 2 i_clk cycles  (state 010)
    //   SET_VCO:   1 i_clk cycle   (state 011, transient)
    //   WAIT_10A:  10 i_clk cycles (state 100)
    //   SET_AMPS:  1 i_clk cycle   (state 101, transient)
    //   WAIT_10B:  10 i_clk cycles (state 110)
    //   DONE:      state 111
    //   Total: ~26 i_clk cycles minimum
    //
    // We wait 50 cycles for generous margin, then check all at once.
    // -------------------------
    task wait_and_check;
        input [1:0] exp_gainA1;
        input [2:0] exp_gainA2;
        begin
            // Wait for full sequence to complete
            // 50 cycles >> 26 cycle minimum — no timing edge cases
            repeat(50) @(posedge i_clk);

            $display("  [t=%0t] Checking all outputs after full sequence:", $time);

            if (o_resetbvco !== 1)
                $display("  FAIL o_resetbvco: got %b, expected 1", o_resetbvco);
            else
                $display("  PASS o_resetbvco=1");

            if (o_resetb1 !== 1)
                $display("  FAIL o_resetb1:   got %b, expected 1", o_resetb1);
            else
                $display("  PASS o_resetb1=1");

            if (o_resetb2 !== 1)
                $display("  FAIL o_resetb2:   got %b, expected 1", o_resetb2);
            else
                $display("  PASS o_resetb2=1");

            if (o_ready !== 1)
                $display("  FAIL o_ready:     got %b, expected 1", o_ready);
            else
                $display("  PASS o_ready=1");

            if (o_gainA1 !== exp_gainA1)
                $display("  FAIL o_gainA1:    got %b, expected %b", o_gainA1, exp_gainA1);
            else
                $display("  PASS o_gainA1=%b", o_gainA1);

            if (o_gainA2 !== exp_gainA2)
                $display("  FAIL o_gainA2:    got %b, expected %b", o_gainA2, exp_gainA2);
            else
                $display("  PASS o_gainA2=%b", o_gainA2);
        end
    endtask

    // -------------------------
    // Main Tests
    // -------------------------
    initial begin
        $dumpfile("tb_backend.vcd");
        $dumpvars(0, tb_backend);

        i_resetbAll = 0;
        i_sclk      = 1;
        i_sdin      = 0;
        i_vco_clk   = 0;
        #10;

        // ===================================================
        // TEST 1: Reset state — all outputs must be 0
        // ===================================================
        $display("\n=== TEST 1: Reset State ===");
        do_reset;
        if (o_ready!==0 || o_resetb1!==0 || o_resetb2!==0 ||
            o_resetbvco!==0 || o_gainA1!==0 || o_gainA2!==0)
            $display("  FAIL: Outputs not 0 during reset at t=%0t", $time);
        else
            $display("  PASS: All outputs 0 during reset");
        $display("TEST 1 done");

        // ===================================================
        // TEST 2: Normal startup
        // d0=0,d1=1,d2=1,d3=0,d4=1
        // gainA1={d1,d0}=2'b10, gainA2={d4,d3,d2}=3'b101
        // ===================================================
        $display("\n=== TEST 2: Normal startup - gainA1=2'b10, gainA2=3'b101 ===");
        @(posedge i_clk); #1;
        i_resetbAll = 1;
        repeat(3) @(posedge i_clk);
        send_serial(5'b10110); // d0=0,d1=1,d2=1,d3=0,d4=1
        wait_and_check(2'b10, 3'b101);
        $display("TEST 2 done");

        // ===================================================
        // TEST 3: Outputs hold in DONE state
        // ===================================================
        $display("\n=== TEST 3: Outputs hold in DONE state ===");
        repeat(50) @(posedge i_clk);
        if (o_ready===1 && o_resetb1===1 && o_resetb2===1 &&
            o_resetbvco===1 && o_gainA1===2'b10 && o_gainA2===3'b101)
            $display("  PASS: All outputs held after 50 extra cycles");
        else
            $display("  FAIL: Outputs changed unexpectedly at t=%0t", $time);
        $display("TEST 3 done");

        // ===================================================
        // TEST 4: Re-reset clears all outputs
        // ===================================================
        $display("\n=== TEST 4: Re-reset behavior ===");
        do_reset;
        if (o_ready!==0 || o_resetb1!==0 || o_resetb2!==0 || o_resetbvco!==0)
            $display("  FAIL: FSM outputs not cleared at t=%0t", $time);
        else
            $display("  PASS: FSM outputs cleared to 0");
        if (o_gainA1!==0 || o_gainA2!==0)
            $display("  FAIL: Gain outputs not cleared at t=%0t", $time);
        else
            $display("  PASS: Gain outputs cleared to 0");
        $display("TEST 4 done");

        // ===================================================
        // TEST 5: All-ones gains
        // d0=1,d1=1,d2=1,d3=1,d4=1
        // gainA1=2'b11, gainA2=3'b111
        // ===================================================
        $display("\n=== TEST 5: All-ones gains - gainA1=2'b11, gainA2=3'b111 ===");
        @(posedge i_clk); #1;
        i_resetbAll = 1;
        repeat(3) @(posedge i_clk);
        send_serial(5'b11111);
        wait_and_check(2'b11, 3'b111);
        $display("TEST 5 done");

        // ===================================================
        // TEST 6: All-zero gains
        // d0=0,d1=0,d2=0,d3=0,d4=0
        // gainA1=2'b00, gainA2=3'b000
        // ===================================================
        $display("\n=== TEST 6: All-zero gains - gainA1=2'b00, gainA2=3'b000 ===");
        do_reset;
        @(posedge i_clk); #1;
        i_resetbAll = 1;
        repeat(3) @(posedge i_clk);
        send_serial(5'b00000);
        wait_and_check(2'b00, 3'b000);
        $display("TEST 6 done");

        // ===================================================
        // TEST 7: Mid-sequence reset aborts cleanly
        // ===================================================
        $display("\n=== TEST 7: Mid-sequence reset ===");
        do_reset;
        @(posedge i_clk); #1;
        i_resetbAll = 1;
        repeat(3) @(posedge i_clk);
        send_serial(5'b10101);

        // Sequence is now running. Wait until VCO is released
        // then interrupt before amps are released
        repeat(8) @(posedge i_clk);
        $display("  Asserting reset mid-sequence (VCO released, amps not yet) at t=%0t", $time);
        do_reset;

        if (o_ready!==0 || o_resetb1!==0 || o_resetb2!==0 || o_resetbvco!==0)
            $display("  FAIL: Outputs not cleared after mid-sequence reset at t=%0t", $time);
        else
            $display("  PASS: All outputs cleared after mid-sequence reset");
        $display("TEST 7 done");

        // ===================================================
        // TEST 8: Full recovery after mid-sequence reset
        // d0=1,d1=0,d2=0,d3=1,d4=0
        // gainA1={d1,d0}=2'b01, gainA2={d4,d3,d2}=3'b010
        // ===================================================
        $display("\n=== TEST 8: Recovery after mid-sequence reset ===");
        @(posedge i_clk); #1;
        i_resetbAll = 1;
        repeat(3) @(posedge i_clk);
        send_serial(5'b01001); // d0=1,d1=0,d2=0,d3=1,d4=0
        wait_and_check(2'b01, 3'b010);
        $display("TEST 8 done");

        // ===================================================
        // TEST 9: Alternating bits
        // d0=1,d1=0,d2=1,d3=0,d4=1
        // gainA1={d1,d0}=2'b01, gainA2={d4,d3,d2}=3'b101
        // ===================================================
        $display("\n=== TEST 9: Alternating bits - gainA1=2'b01, gainA2=3'b101 ===");
        do_reset;
        @(posedge i_clk); #1;
        i_resetbAll = 1;
        repeat(3) @(posedge i_clk);
        send_serial(5'b10101); // d0=1,d1=0,d2=1,d3=0,d4=1
        wait_and_check(2'b01, 3'b101);
        $display("TEST 9 done");

        $display("\n=== ALL TESTS COMPLETE ===");
        #100;
        $finish;
    end

    // -------------------------
    // Timeout watchdog
    // -------------------------
    initial begin
        #2_000_000;
        $display("TIMEOUT at t=%0t", $time);
        $finish;
    end

endmodule

tb_backend.vcd
$date
	Sat Mar  7 16:15:36 2026
$end
$version
	Icarus Verilog
$end
$timescale
	1ps
$end
$scope module tb_backend $end
$var wire 1 ! o_resetbvco $end
$var wire 1 " o_resetb2 $end
$var wire 1 # o_resetb1 $end
$var wire 1 $ o_ready $end
$var wire 3 % o_gainA2 [2:0] $end
$var wire 2 & o_gainA1 [1:0] $end
$var reg 1 ' i_clk $end
$var reg 1 ( i_resetbAll $end
$var reg 1 ) i_sclk $end
$var reg 1 * i_sdin $end
$var reg 1 + i_vco_clk $end
$scope module dut $end
$var wire 1 ' i_clk $end
$var wire 1 ( i_resetbAll $end
$var wire 1 ) i_sclk $end
$var wire 1 * i_sdin $end
$var wire 1 + i_vco_clk $end
$var wire 1 , ready_serial $end
$var wire 1 ! o_resetbvco $end
$var wire 1 " o_resetb2 $end
$var wire 1 # o_resetb1 $end
$var wire 1 $ o_ready $end
$var wire 3 - o_gainA2 [2:0] $end
$var wire 2 . o_gainA1 [1:0] $end
$scope module fsm $end
$var wire 1 ' i_clk $end
$var wire 1 ( reset_all $end
$var wire 1 , ready_serial $end
$var parameter 3 / DONE $end
$var parameter 3 0 RST $end
$var parameter 3 1 SET_AMPS $end
$var parameter 3 2 SET_VCO $end
$var parameter 3 3 WAIT_10A $end
$var parameter 3 4 WAIT_10B $end
$var parameter 3 5 WAIT_2CYC $end
$var parameter 3 6 WAIT_SERIAL $end
$var reg 4 7 counter [3:0] $end
$var reg 3 8 current_state [2:0] $end
$var reg 3 9 next_state [2:0] $end
$var reg 1 $ o_ready $end
$var reg 1 # o_resetb1 $end
$var reg 1 " o_resetb2 $end
$var reg 1 ! o_resetbvco $end
$var reg 1 : ready_sync1 $end
$var reg 1 ; ready_sync2 $end
$upscope $end
$scope module ser $end
$var wire 1 ( i_reset $end
$var wire 1 ) i_sclk $end
$var wire 1 * i_sdin $end
$var reg 3 < count [2:0] $end
$var reg 5 = d [4:0] $end
$var reg 1 > final_stop $end
$var reg 2 ? o_gainA1 [1:0] $end
$var reg 3 @ o_gainA2 [2:0] $end
$var reg 1 , ready_serial $end
$var reg 1 A stop $end
$upscope $end
$upscope $end
$scope task do_reset $end
$var integer 32 B i [31:0] $end
$upscope $end
$scope task send_serial $end
$var reg 5 C data [4:0] $end
$var integer 32 D i [31:0] $end
$upscope $end
$scope task wait_and_check_done $end
$var reg 2 E exp_gainA1 [1:0] $end
$var reg 3 F exp_gainA2 [2:0] $end
$upscope $end
$upscope $end
$enddefinitions $end
$comment Show the parameter values. $end
$dumpall
b1 6
b10 5
b110 4
b100 3
b11 2
b101 1
b0 0
b111 /
$end
#0
$dumpvars
bx F
bx E
bx D
bx C
b0 B
0A
b0 @
b0 ?
0>
b0 =
b0 <
x;
x:
b0 9
bx 8
bx 7
b0 .
b0 -
0,
0+
0*
1)
0(
0'
b0 &
b0 %
0$
0#
0"
0!
$end
#2500
0;
0:
b0 8
b0 7
1'
#5000
0'
#7500
1'
#10000
0'
#12500
1'
#15000
0'
#17500
1'
#20000
0'
#22500
1'
#25000
0'
#27500
1'
#30000
0'
#32500
1'
#35000
0'
#37500
1'
#40000
0'
#42500
1'
#45000
0'
#47500
1'
#50000
0'
#52500
1'
#55000
0'
#57500
1'
#60000
0'
#62500
1'
#65000
0'
#67500
1'
#70000
0'
#72500
1'
#75000
0'
#77500
1'
#80000
0'
#82500
1'
#85000
0'
#87500
1'
#90000
0'
#92500
1'
#95000
0'
#97500
1'
#100000
0'
0)
#102500
1'
#105000
0'
#107500
1'
#110000
0'
#112500
1'
#115000
0'
#117500
1'
#120000
0'
#122500
1'
#125000
0'
#127500
1'
#130000
0'
#132500
1'
#135000
0'
#137500
1'
#140000
0'
#142500
1'
#145000
0'
#147500
1'
#150000
0'
#152500
1'
#155000
0'
#157500
1'
#160000
0'
#162500
1'
#165000
0'
#167500
1'
#170000
0'
#172500
1'
#175000
0'
#177500
1'
#180000
0'
#182500
1'
#185000
0'
#187500
1'
#190000
0'
#192500
1'
#195000
0'
#197500
1'
#200000
0'
b1 B
1)
#202500
1'
#205000
0'
#207500
1'
#210000
0'
#212500
1'
#215000
0'
#217500
1'
#220000
0'
#222500
1'
#225000
0'
#227500
1'
#230000
0'
#232500
1'
#235000
0'
#237500
1'
#240000
0'
#242500
1'
#245000
0'
#247500
1'
#250000
0'
#252500
1'
#255000
0'
#257500
1'
#260000
0'
#262500
1'
#265000
0'
#267500
1'
#270000
0'
#272500
1'
#275000
0'
#277500
1'
#280000
0'
#282500
1'
#285000
0'
#287500
1'
#290000
0'
#292500
1'
#295000
0'
#297500
1'
#300000
0'
0)
#302500
1'
#305000
0'
#307500
1'
#310000
0'
#312500
1'
#315000
0'
#317500
1'
#320000
0'
#322500
1'
#325000
0'
#327500
1'
#330000
0'
#332500
1'
#335000
0'
#337500
1'
#340000
0'
#342500
1'
#345000
0'
#347500
1'
#350000
0'
#352500
1'
#355000
0'
#357500
1'
#360000
0'
#362500
1'
#365000
0'
#367500
1'
#370000
0'
#372500
1'
#375000
0'
#377500
1'
#380000
0'
#382500
1'
#385000
0'
#387500
1'
#390000
0'
#392500
1'
#395000
0'
#397500
1'
#400000
0'
b10 B
1)
#402500
1'
#405000
0'
#407500
1'
#410000
0'
#412500
1'
#415000
0'
#417500
1'
#420000
0'
#422500
1'
#425000
0'
#427500
1'
#430000
0'
#432500
1'
#435000
0'
#437500
1'
#440000
0'
#442500
1'
#445000
0'
#447500
1'
#450000
0'
#452500
1'
#455000
0'
#457500
1'
#460000
0'
#462500
1'
#465000
0'
#467500
1'
#470000
0'
#472500
1'
#475000
0'
#477500
1'
#480000
0'
#482500
1'
#485000
0'
#487500
1'
#490000
0'
#492500
1'
#495000
0'
#497500
1'
#500000
0'
0)
#502500
1'
#505000
0'
#507500
1'
#510000
0'
#512500
1'
#515000
0'
#517500
1'
#520000
0'
#522500
1'
#525000
0'
#527500
1'
#530000
0'
#532500
1'
#535000
0'
#537500
1'
#540000
0'
#542500
1'
#545000
0'
#547500
1'
#550000
0'
#552500
1'
#555000
0'
#557500
1'
#560000
0'
#562500
1'
#565000
0'
#567500
1'
#570000
0'
#572500
1'
#575000
0'
#577500
1'
#580000
0'
#582500
1'
#585000
0'
#587500
1'
#590000
0'
#592500
1'
#595000
0'
#597500
1'
#600000
0'
b11 B
1)
#602500
1'
#605000
0'
#607500
1'
#610000
0'
#612500
1'
#615000
0'
#617500
1'
#620000
0'
#622500
1'
#625000
0'
#627500
1'
#630000
0'
#632500
1'
#635000
0'
#637500
1'
#640000
0'
#642500
1'
#645000
0'
#647500
1'
#650000
0'
#652500
1'
#655000
0'
#657500
1'
#660000
0'
#662500
1'
#665000
0'
#667500
1'
#670000
0'
#672500
1'
#675000
0'
#677500
1'
#680000
0'
#682500
1'
#685000
0'
#687500
1'
#690000
0'
#692500
1'
#695000
0'
#697500
1'
#700000
0'
0)
#702500
1'
#705000
0'
#707500
1'
#710000
0'
#712500
1'
#715000
0'
#717500
1'
#720000
0'
#722500
1'
#725000
0'
#727500
1'
#730000
0'
#732500
1'
#735000
0'
#737500
1'
#740000
0'
#742500
1'
#745000
0'
#747500
1'
#750000
0'
#752500
1'
#755000
0'
#757500
1'
#760000
0'
#762500
1'
#765000
0'
#767500
1'
#770000
0'
#772500
1'
#775000
0'
#777500
1'
#780000
0'
#782500
1'
#785000
0'
#787500
1'
#790000
0'
#792500
1'
#795000
0'
#797500
1'
#800000
0'
b100 B
1)
#802500
1'
#805000
0'
#807500
1'
#810000
0'
#812500
1'
#815000
0'
#817500
1'
#820000
0'
#822500
1'
#825000
0'
#827500
1'
#830000
0'
#832500
1'
#835000
0'
#837500
1'
#840000
0'
#842500
1'
#845000
0'
#847500
1'
#850000
0'
#852500
1'
#855000
0'
#857500
1'
#860000
0'
#862500
1'
#865000
0'
#867500
1'
#870000
0'
#872500
1'
#875000
0'
#877500
1'
#880000
0'
#882500
1'
#885000
0'
#887500
1'
#890000
0'
#892500
1'
#895000
0'
#897500
1'
#900000
0'
0)
#902500
1'
#905000
0'
#907500
1'
#910000
0'
#912500
1'
#915000
0'
#917500
1'
#920000
0'
#922500
1'
#925000
0'
#927500
1'
#930000
0'
#932500
1'
#935000
0'
#937500
1'
#940000
0'
#942500
1'
#945000
0'
#947500
1'
#950000
0'
#952500
1'
#955000
0'
#957500
1'
#960000
0'
#962500
1'
#965000
0'
#967500
1'
#970000
0'
#972500
1'
#975000
0'
#977500
1'
#980000
0'
#982500
1'
#985000
0'
#987500
1'
#990000
0'
#992500
1'
#995000
0'
#997500
1'
#1000000
0'
b101 B
1)
#1002500
1'
#1005000
0'
#1007500
1'
#1010000
0'
#1012500
1'
#1015000
0'
#1017500
1'
#1020000
0'
#1022500
1'
#1025000
0'
#1027500
1'
#1030000
0'
#1032500
1'
#1035000
0'
#1037500
1'
#1040000
0'
#1042500
1'
#1045000
0'
#1047500
1'
#1050000
0'
#1052500
1'
#1055000
0'
#1057500
1'
#1060000
0'
#1062500
1'
#1065000
0'
#1067500
1'
#1070000
0'
#1072500
1'
#1075000
0'
#1077500
1'
#1080000
0'
#1082500
1'
#1085000
0'
#1087500
1'
#1090000
0'
#1092500
1'
#1095000
0'
#1097500
1'
#1100000
0'
0)
#1102500
1'
#1105000
0'
#1107500
1'
#1110000
0'
#1112500
1'
#1115000
0'
#1117500
1'
#1120000
0'
#1122500
1'
#1125000
0'
#1127500
1'
#1130000
0'
#1132500
1'
#1135000
0'
#1137500
1'
#1140000
0'
#1142500
1'
#1145000
0'
#1147500
1'
#1150000
0'
#1152500
1'
#1155000
0'
#1157500
1'
#1160000
0'
#1162500
1'
#1165000
0'
#1167500
1'
#1170000
0'
#1172500
1'
#1175000
0'
#1177500
1'
#1180000
0'
#1182500
1'
#1185000
0'
#1187500
1'
#1190000
0'
#1192500
1'
#1195000
0'
#1197500
1'
#1200000
0'
b110 B
1)
#1202500
1'
#1205000
0'
#1207500
1'
#1210000
0'
#1212500
1'
#1215000
0'
#1217500
1'
#1218500
b1 9
1(
#1220000
0'
#1222500
b1 8
1'
#1225000
0'
#1227500
b1 7
1'
#1230000
0'
#1232500
b10 7
1'
#1235000
0'
#1237500
b11 7
1'
#1240000
0'
#1242500
b100 7
1'
#1245000
0'
#1247500
b101 7
1'
#1250000
0'
#1252500
b110 7
1'
#1255000
0'
#1257500
b111 7
1'
#1260000
0'
#1262500
b1000 7
1'
#1265000
0'
#1267500
b1001 7
1'
#1268500
b0 D
b10110 C
#1270000
0'
#1272500
b1010 7
1'
#1275000
0'
#1277500
b1011 7
1'
#1280000
0'
#1282500
b1100 7
1'
#1285000
0'
#1287500
b1101 7
1'
#1290000
0'
#1292500
b1110 7
1'
#1295000
0'
#1297500
b1111 7
1'
#1300000
0'
#1302500
b0 7
1'
#1305000
0'
#1307500
b1 7
1'
#1310000
0'
#1312500
b10 7
1'
#1315000
0'
#1317500
b11 7
1'
#1320000
0'
#1322500
b100 7
1'
#1325000
0'
#1327500
b101 7
1'
#1330000
0'
#1332500
b110 7
1'
#1335000
0'
#1337500
b111 7
1'
#1340000
0'
#1342500
b1000 7
1'
#1345000
0'
#1347500
b1001 7
1'
#1350000
0'
#1352500
b1010 7
1'
#1355000
0'
#1357500
b1011 7
1'
#1360000
0'
#1362500
b1100 7
1'
#1365000
0'
#1367500
b1101 7
1'
#1368500
0)
#1370000
0'
#1372500
b1110 7
1'
#1375000
0'
#1377500
b1111 7
1'
#1380000
0'
#1382500
b0 7
1'
#1385000
0'
#1387500
b1 7
1'
#1390000
0'
#1392500
b10 7
1'
#1395000
0'
#1397500
b11 7
1'
#1400000
0'
#1402500
b100 7
1'
#1405000
0'
#1407500
b101 7
1'
#1410000
0'
#1412500
b110 7
1'
#1415000
0'
#1417500
b111 7
1'
#1420000
0'
#1422500
b1000 7
1'
#1425000
0'
#1427500
b1001 7
1'
#1430000
0'
#1432500
b1010 7
1'
#1435000
0'
#1437500
b1011 7
1'
#1440000
0'
#1442500
b1100 7
1'
#1445000
0'
#1447500
b1101 7
1'
#1450000
0'
#1452500
b1110 7
1'
#1455000
0'
#1457500
b1111 7
1'
#1460000
0'
#1462500
b0 7
1'
#1465000
0'
#1467500
b1 7
1'
#1468500
b1 <
b1 D
1)
#1470000
0'
#1472500
b10 7
1'
#1475000
0'
#1477500
b11 7
1'
#1480000
0'
#1482500
b100 7
1'
#1485000
0'
#1487500
b101 7
1'
#1490000
0'
#1492500
b110 7
1'
#1495000
0'
#1497500
b111 7
1'
#1500000
0'
#1502500
b1000 7
1'
#1505000
0'
#1507500
b1001 7
1'
#1510000
0'
#1512500
b1010 7
1'
#1515000
0'
#1517500
b1011 7
1'
#1520000
0'
#1522500
b1100 7
1'
#1525000
0'
#1527500
b1101 7
1'
#1530000
0'
#1532500
b1110 7
1'
#1535000
0'
#1537500
b1111 7
1'
#1540000
0'
#1542500
b0 7
1'
#1545000
0'
#1547500
b1 7
1'
#1550000
0'
#1552500
b10 7
1'
#1555000
0'
#1557500
b11 7
1'
#1560000
0'
#1562500
b100 7
1'
#1565000
0'
#1567500
b101 7
1'
#1568500
1*
0)
#1570000
0'
#1572500
b110 7
1'
#1575000
0'
#1577500
b111 7
1'
#1580000
0'
#1582500
b1000 7
1'
#1585000
0'
#1587500
b1001 7
1'
#1590000
0'
#1592500
b1010 7
1'
#1595000
0'
#1597500
b1011 7
1'
#1600000
0'
#1602500
b1100 7
1'
#1605000
0'
#1607500
b1101 7
1'
#1610000
0'
#1612500
b1110 7
1'
#1615000
0'
#1617500
b1111 7
1'
#1620000
0'
#1622500
b0 7
1'
#1625000
0'
#1627500
b1 7
1'
#1630000
0'
#1632500
b10 7
1'
#1635000
0'
#1637500
b11 7
1'
#1640000
0'
#1642500
b100 7
1'
#1645000
0'
#1647500
b101 7
1'
#1650000
0'
#1652500
b110 7
1'
#1655000
0'
#1657500
b111 7
1'
#1660000
0'
#1662500
b1000 7
1'
#1665000
0'
#1667500
b1001 7
1'
#1668500
b10 <
b10 =
b10 D
1)
#1670000
0'
#1672500
b1010 7
1'
#1675000
0'
#1677500
b1011 7
1'
#1680000
0'
#1682500
b1100 7
1'
#1685000
0'
#1687500
b1101 7
1'
#1690000
0'
#1692500
b1110 7
1'
#1695000
0'
#1697500
b1111 7
1'
#1700000
0'
#1702500
b0 7
1'
#1705000
0'
#1707500
b1 7
1'
#1710000
0'
#1712500
b10 7
1'
#1715000
0'
#1717500
b11 7
1'
#1720000
0'
#1722500
b100 7
1'
#1725000
0'
#1727500
b101 7
1'
#1730000
0'
#1732500
b110 7
1'
#1735000
0'
#1737500
b111 7
1'
#1740000
0'
#1742500
b1000 7
1'
#1745000
0'
#1747500
b1001 7
1'
#1750000
0'
#1752500
b1010 7
1'
#1755000
0'
#1757500
b1011 7
1'
#1760000
0'
#1762500
b1100 7
1'
#1765000
0'
#1767500
b1101 7
1'
#1768500
0)
#1770000
0'
#1772500
b1110 7
1'
#1775000
0'
#1777500
b1111 7
1'
#1780000
0'
#1782500
b0 7
1'
#1785000
0'
#1787500
b1 7
1'
#1790000
0'
#1792500
b10 7
1'
#1795000
0'
#1797500
b11 7
1'
#1800000
0'
#1802500
b100 7
1'
#1805000
0'
#1807500
b101 7
1'
#1810000
0'
#1812500
b110 7
1'
#1815000
0'
#1817500
b111 7
1'
#1820000
0'
#1822500
b1000 7
1'
#1825000
0'
#1827500
b1001 7
1'
#1830000
0'
#1832500
b1010 7
1'
#1835000
0'
#1837500
b1011 7
1'
#1840000
0'
#1842500
b1100 7
1'
#1845000
0'
#1847500
b1101 7
1'
#1850000
0'
#1852500
b1110 7
1'
#1855000
0'
#1857500
b1111 7
1'
#1860000
0'
#1862500
b0 7
1'
#1865000
0'
