startup.v
// This is the file where the FSM design would be created 

module startup_fsm(
    input reset_all, //Active low 
    input i_clk,
    input ready_serial, // This would come from the serial_comm module showing data has been transferred 
    output reg o_ready,
    output reg o_resetb1,  //Active low for amp1
    output reg o_resetb2, //Active low for amp2
    output reg o_resetbvco //Active low for VCO
);

// We need to handle the clock domain crossing part. 
// Ready serial comes from i_sclk clock and now we have a high freq i_clk
// This needs to be taken care of using a synchornizer 

    reg ready_sync1, ready_sync2;

    always @(posedge i_clk) begin
        if (!reset_all) begin
            ready_sync1 <= 0;
            ready_sync2 <= 0;
        end else begin
            ready_sync1 <= ready_serial;
            ready_sync2 <= ready_sync1;
        end
    end

    // Now we can start with the actual FSM now that CDC is handeled 
    
    // State encoding. We have 8 states (2 of these are similar so they might be reducable)
    // I am doing a Moore implementation now, but a Mealey can be done to save the last state
    // But still we would need 3 flip flops even in moore
    parameter RST=3'b000; //reset_all
    parameter WAIT_SERIAL =3'b001; //wait_serial
    parameter WAIT_2CYC = 3'b010;
    parameter SET_VCO = 3'b011;
    parameter WAIT_10A = 3'b100;
    parameter SET_AMPS = 3'b101;
    parameter WAIT_10B = 3'b110;
    parameter DONE = 3'b111;

    //Registers for FSM
    reg [2:0] current_state, next_state;
    reg [3:0] counter; // counter for the delay blocks

    // Sequential logic to update states

    always @(posedge i_clk) begin //The PS does not mention a reset type. Assuming synchronous reset for simplicity

    if(!reset_all) begin 
        counter <= 0;
        current_state <= RST; //Since active low, this handles reset here so we wont have to do it again and again in each state
    end

    else begin 
        current_state <= next_state;
        if (current_state != next_state) begin //during transitions
            counter <= 0;
        end

        else counter <= counter + 1; //increment counter to find delay
    end

    end

    //Combinational logic that just sets the next state and all corresponding outputs

    always @(*) begin
        // default outputs
        o_ready = 0;
        o_resetb1 = 0;
        o_resetb2 = 0;
        o_resetbvco = 0;

        next_state = current_state;
        case(current_state)
            RST: begin
                // Reset all backend outputs and other regs
                o_ready = 0;
                o_resetb1 = 0;
                o_resetb2 = 0;
                o_resetbvco = 0;

                if(reset_all) next_state = WAIT_SERIAL;

            end

            WAIT_SERIAL: begin 
                // serial comm would happen and set the ready-serial high, which after CDC synchronization has become ready_sync2
                if (ready_sync2) next_state = WAIT_2CYC;

            end

            WAIT_2CYC: begin
                if (counter == 2) next_state = SET_VCO; //counter set in the sequential block above
            end

            SET_VCO: begin 
                o_resetbvco = 1;
                next_state = WAIT_10A;

            end

            WAIT_10A: begin
                o_resetbvco = 1;
                if (counter == 10) next_state = SET_AMPS;
            end

            SET_AMPS: begin 
                o_resetbvco = 1;
                o_resetb1 = 1;
                o_resetb2 = 1;
                next_state = WAIT_10B;
            end

            WAIT_10B: begin 
                o_resetbvco = 1;
                o_resetb1 = 1;
                o_resetb2 = 1;
                if (counter == 10) next_state = DONE;
            end

            DONE: begin
                o_resetbvco = 1;
                o_resetb1 = 1;
                o_resetb2 = 1; // Hold all values
                o_ready = 1; // Chip is ready!
            end

            default: next_state = RST; //for synthesizability


        endcase

    end

endmodule

serial.v
module serial_comm (
    input i_sclk,
    input i_sdin,
    input i_reset, // this will be an active low synchronous reset
    output reg [1:0] o_gainA1,
    output reg [2:0] o_gainA2,
    output reg ready_serial
);

reg [4:0] d; 
reg [2:0] count;
reg stop, final_stop;

always @(posedge i_sclk or negedge i_reset) begin //asynch reset

    if(!i_reset) begin 
        d <= 0;
        ready_serial <= 0;
        o_gainA1 <= 0;
        o_gainA2 <= 0;
        count <= 0;
        stop <= 0;
        final_stop <= 0;
    end

    else if (stop & !(final_stop)) begin 
        // I am updating the gains one clk edge after the 5th clk edge 
        // this is done solely for ease of design. 
        o_gainA1[0] <= d[0];
        o_gainA1[1] <= d[1];
        o_gainA2[0] <= d[2];
        o_gainA2[1] <= d[3];
        o_gainA2[2] <= d[4];
        ready_serial <= 1;
        final_stop <= 1; // this will now ensure that gains are assigned only once
    end

    else if (!stop) begin 

        // Sample the input
        d[count] <= i_sdin;

        count <= count + 1;
        if(count == (3'b100)) stop <= 1;

    end

end

endmodule

main.v
// This is the main file where we will connect all blocks

/*
EE619 project 1 
Submitted by - Samarth Sharma Bhardwaj (230903)
*/

module backend(
    input i_resetbAll, i_clk, i_sclk, i_sdin, i_vco_clk,
    output o_resetb1, o_resetb2, o_resetbvco, o_ready,
    output [1:0] o_gainA1,
    output [2:0] o_gainA2
);

    wire ready_serial;

    // Instantiate the modules

    serial_comm ser(
    .i_sclk(i_sclk),
    .i_sdin(i_sdin),
    .i_reset(i_resetbAll),
    .o_gainA1(o_gainA1),
    .o_gainA2(o_gainA2),
    .ready_serial(ready_serial)
    );

    startup_fsm fsm(
        .reset_all(i_resetbAll),
        .i_clk(i_clk),
        .ready_serial(ready_serial),
        .o_ready(o_ready),
        .o_resetb1(o_resetb1),
        .o_resetb2(o_resetb2),
        .o_resetbvco(o_resetbvco)
    );

endmodule

tb.v
`timescale 1ns/1ps

module tb_backend;

reg i_resetbAll;
reg i_clk;
reg i_sclk;
reg i_sdin;
reg i_vco_clk;

wire o_resetb1;
wire o_resetb2;
wire o_resetbvco;
wire o_ready;
wire [1:0] o_gainA1;
wire [2:0] o_gainA2;


backend dut(
    .i_resetbAll(i_resetbAll),
    .i_clk(i_clk),
    .i_sclk(i_sclk),
    .i_sdin(i_sdin),
    .i_vco_clk(i_vco_clk),
    .o_resetb1(o_resetb1),
    .o_resetb2(o_resetb2),
    .o_resetbvco(o_resetbvco),
    .o_ready(o_ready),
    .o_gainA1(o_gainA1),
    .o_gainA2(o_gainA2)
);

//////////////////////////////////////////////////
// CLOCKS
//////////////////////////////////////////////////

initial i_clk = 0;
always #2.5 i_clk = ~i_clk;   // 200 MHz

initial i_sclk = 1;


//////////////////////////////////////////////////
// SERIAL SEND TASK
//////////////////////////////////////////////////

task send_serial;
input [4:0] data;
integer i;
begin
    for(i=0;i<5;i=i+1) begin
        #100 i_sclk = 0;
        i_sdin = data[i];
        #100 i_sclk = 1;
    end
end
endtask


//////////////////////////////////////////////////
// MAIN TEST
//////////////////////////////////////////////////

initial begin

    $dumpfile("wave.vcd");
    $dumpvars(0,tb_backend);

    i_resetbAll = 0;
    i_sdin = 0;
    i_vco_clk = 0;

    // reset
    repeat(5) @(posedge i_clk);

    // release reset
    i_resetbAll = 1;

    // send data
    // d0=0 d1=1 d2=1 d3=0 d4=1
    send_serial(5'b10110);

    // wait long enough for FSM
    repeat(50) @(posedge i_clk);
    $monitor("t=%0t sdin=%b count=%d gains=%b %b ready=%b",
         $time, i_sdin, dut.ser.count, o_gainA1, o_gainA2, dut.ser.ready_serial);

    $display("gainA1 = %b",o_gainA1);
    $display("gainA2 = %b",o_gainA2);
    $display("resetbvco = %b",o_resetbvco);
    $display("resetb1 = %b",o_resetb1);
    $display("resetb2 = %b",o_resetb2);
    $display("ready = %b",o_ready);

    $finish;

end

endmodule

wave.vcd
$date
	Sat Mar  7 16:21:25 2026
$end
$version
	Icarus Verilog
$end
$timescale
	1ps
$end
$scope module tb_backend $end
$var wire 1 ! o_resetbvco $end
$var wire 1 " o_resetb2 $end
$var wire 1 # o_resetb1 $end
$var wire 1 $ o_ready $end
$var wire 3 % o_gainA2 [2:0] $end
$var wire 2 & o_gainA1 [1:0] $end
$var reg 1 ' i_clk $end
$var reg 1 ( i_resetbAll $end
$var reg 1 ) i_sclk $end
$var reg 1 * i_sdin $end
$var reg 1 + i_vco_clk $end
$scope module dut $end
$var wire 1 ' i_clk $end
$var wire 1 ( i_resetbAll $end
$var wire 1 ) i_sclk $end
$var wire 1 * i_sdin $end
$var wire 1 + i_vco_clk $end
$var wire 1 , ready_serial $end
$var wire 1 ! o_resetbvco $end
$var wire 1 " o_resetb2 $end
$var wire 1 # o_resetb1 $end
$var wire 1 $ o_ready $end
$var wire 3 - o_gainA2 [2:0] $end
$var wire 2 . o_gainA1 [1:0] $end
$scope module fsm $end
$var wire 1 ' i_clk $end
$var wire 1 ( reset_all $end
$var wire 1 , ready_serial $end
$var parameter 3 / DONE $end
$var parameter 3 0 RST $end
$var parameter 3 1 SET_AMPS $end
$var parameter 3 2 SET_VCO $end
$var parameter 3 3 WAIT_10A $end
$var parameter 3 4 WAIT_10B $end
$var parameter 3 5 WAIT_2CYC $end
$var parameter 3 6 WAIT_SERIAL $end
$var reg 4 7 counter [3:0] $end
$var reg 3 8 current_state [2:0] $end
$var reg 3 9 next_state [2:0] $end
$var reg 1 $ o_ready $end
$var reg 1 # o_resetb1 $end
$var reg 1 " o_resetb2 $end
$var reg 1 ! o_resetbvco $end
$var reg 1 : ready_sync1 $end
$var reg 1 ; ready_sync2 $end
$upscope $end
$scope module ser $end
$var wire 1 ( i_reset $end
$var wire 1 ) i_sclk $end
$var wire 1 * i_sdin $end
$var reg 3 < count [2:0] $end
$var reg 5 = d [4:0] $end
$var reg 1 > final_stop $end
$var reg 2 ? o_gainA1 [1:0] $end
$var reg 3 @ o_gainA2 [2:0] $end
$var reg 1 , ready_serial $end
$var reg 1 A stop $end
$upscope $end
$upscope $end
$scope task send_serial $end
$var reg 5 B data [4:0] $end
$var integer 32 C i [31:0] $end
$upscope $end
$upscope $end
$enddefinitions $end
$comment Show the parameter values. $end
$dumpall
b1 6
b10 5
b110 4
b100 3
b11 2
b101 1
b0 0
b111 /
$end
#0
$dumpvars
bx C
bx B
0A
b0 @
b0 ?
0>
b0 =
b0 <
x;
x:
b0 9
bx 8
bx 7
b0 .
b0 -
0,
0+
0*
1)
0(
0'
b0 &
b0 %
0$
0#
0"
0!
$end
#2500
0;
0:
b0 8
b0 7
1'
#5000
0'
#7500
1'
#10000
0'
#12500
1'
#15000
0'
#17500
1'
#20000
0'
#22500
b1 7
b1 9
b0 C
b10110 B
1(
1'
#25000
0'
#27500
b0 7
b1 8
1'
#30000
0'
#32500
b1 7
1'
#35000
0'
#37500
b10 7
1'
#40000
0'
#42500
b11 7
1'
#45000
0'
#47500
b100 7
1'
#50000
0'
#52500
b101 7
1'
#55000
0'
#57500
b110 7
1'
#60000
0'
#62500
b111 7
1'
#65000
0'
#67500
b1000 7
1'
#70000
0'
#72500
b1001 7
1'
#75000
0'
#77500
b1010 7
1'
#80000
0'
#82500
b1011 7
1'
#85000
0'
#87500
b1100 7
1'
#90000
0'
#92500
b1101 7
1'
#95000
0'
#97500
b1110 7
1'
#100000
0'
#102500
b1111 7
1'
#105000
0'
#107500
b0 7
1'
#110000
0'
#112500
b1 7
1'
#115000
0'
#117500
b10 7
1'
#120000
0'
#122500
b11 7
1'
0)
#125000
0'
#127500
b100 7
1'
#130000
0'
#132500
b101 7
1'
#135000
0'
#137500
b110 7
1'
#140000
0'
#142500
b111 7
1'
#145000
0'
#147500
b1000 7
1'
#150000
0'
#152500
b1001 7
1'
#155000
0'
#157500
b1010 7
1'
#160000
0'
#162500
b1011 7
1'
#165000
0'
#167500
b1100 7
1'
#170000
0'
#172500
b1101 7
1'
#175000
0'
#177500
b1110 7
1'
#180000
0'
#182500
b1111 7
1'
#185000
0'
#187500
b0 7
1'
#190000
0'
#192500
b1 7
1'
#195000
0'
#197500
b10 7
1'
#200000
0'
#202500
b11 7
1'
#205000
0'
#207500
b100 7
1'
#210000
0'
#212500
b101 7
1'
#215000
0'
#217500
b110 7
1'
#220000
0'
#222500
b111 7
b1 <
1'
b1 C
1)
#225000
0'
#227500
b1000 7
1'
#230000
0'
#232500
b1001 7
1'
#235000
0'
#237500
b1010 7
1'
#240000
0'
#242500
b1011 7
1'
#245000
0'
#247500
b1100 7
1'
#250000
0'
#252500
b1101 7
1'
#255000
0'
#257500
b1110 7
1'
#260000
0'
#262500
b1111 7
1'
#265000
0'
#267500
b0 7
1'
#270000
0'
#272500
b1 7
1'
#275000
0'
#277500
b10 7
1'
#280000
0'
#282500
b11 7
1'
#285000
0'
#287500
b100 7
1'
#290000
0'
#292500
b101 7
1'
#295000
0'
#297500
b110 7
1'
#300000
0'
#302500
b111 7
1'
#305000
0'
#307500
b1000 7
1'
#310000
0'
#312500
b1001 7
1'
#315000
0'
#317500
b1010 7
1'
#320000
0'
#322500
b1011 7
1'
1*
0)
#325000
0'
#327500
b1100 7
1'
#330000
0'
#332500
b1101 7
1'
#335000
0'
#337500
b1110 7
1'
#340000
0'
#342500
b1111 7
1'
#345000
0'
#347500
b0 7
1'
#350000
0'
#352500
b1 7
1'
#355000
0'
#357500
b10 7
1'
#360000
0'
#362500
b11 7
1'
#365000
0'
#367500
b100 7
1'
#370000
0'
#372500
b101 7
1'
#375000
0'
#377500
b110 7
1'
#380000
0'
#382500
b111 7
1'
#385000
0'
#387500
b1000 7
1'
#390000
0'
#392500
b1001 7
1'
#395000
0'
#397500
b1010 7
1'
#400000
0'
#402500
b1011 7
1'
#405000
0'
#407500
b1100 7
1'
#410000
0'
#412500
b1101 7
1'
#415000
0'
#417500
b1110 7
1'
#420000
0'
#422500
b1111 7
b10 <
b10 =
1'
b10 C
1)
#425000
0'
#427500
b0 7
1'
#430000
0'
#432500
b1 7
1'
#435000
0'
#437500
b10 7
1'
#440000
0'
#442500
b11 7
1'
#445000
0'
#447500
b100 7
1'
#450000
0'
#452500
b101 7
1'
#455000
0'
#457500
b110 7
1'
#460000
0'
#462500
b111 7
1'
#465000
0'
#467500
b1000 7
1'
#470000
0'
#472500
b1001 7
1'
#475000
0'
#477500
b1010 7
1'
#480000
0'
#482500
b1011 7
1'
#485000
0'
#487500
b1100 7
1'
#490000
0'
#492500
b1101 7
1'
#495000
0'
#497500
b1110 7
1'
#500000
0'
#502500
b1111 7
1'
#505000
0'
#507500
b0 7
1'
#510000
0'
#512500
b1 7
1'
#515000
0'
#517500
b10 7
1'
#520000
0'
#522500
b11 7
1'
0)
#525000
0'
#527500
b100 7
1'
#530000
0'
#532500
b101 7
1'
#535000
0'
#537500
b110 7
1'
#540000
0'
#542500
b111 7
1'
#545000
0'
#547500
b1000 7
1'
#550000
0'
#552500
b1001 7
1'
#555000
0'
#557500
b1010 7
1'
#560000
0'
#562500
b1011 7
1'
#565000
0'
#567500
b1100 7
1'
#570000
0'
#572500
b1101 7
1'
#575000
0'
#577500
b1110 7
1'
#580000
0'
#582500
b1111 7
1'
#585000
0'
#587500
b0 7
1'
#590000
0'
#592500
b1 7
1'
#595000
0'
#597500
b10 7
1'
#600000
0'
#602500
b11 7
1'
#605000
0'
#607500
b100 7
1'
#610000
0'
#612500
b101 7
1'
#615000
0'
#617500
b110 7
1'
#620000
0'
#622500
b111 7
b11 <
b110 =
1'
b11 C
1)
#625000
0'
#627500
b1000 7
1'
#630000
0'
#632500
b1001 7
1'
#635000
0'
#637500
b1010 7
1'
#640000
0'
#642500
b1011 7
1'
#645000
0'
#647500
b1100 7
1'
#650000
0'
#652500
b1101 7
1'
#655000
0'
#657500
b1110 7
1'
#660000
0'
#662500
b1111 7
1'
#665000
0'
#667500
b0 7
1'
#670000
0'
#672500
b1 7
1'
#675000
0'
#677500
b10 7
1'
#680000
0'
#682500
b11 7
1'
#685000
0'
#687500
b100 7
1'
#690000
0'
#692500
b101 7
1'
#695000
0'
#697500
b110 7
1'
#700000
0'
#702500
b111 7
1'
#705000
0'
#707500
b1000 7
1'
#710000
0'
#712500
b1001 7
1'
#715000
0'
#717500
b1010 7
1'
#720000
0'
#722500
b1011 7
1'
0*
0)
#725000
0'
#727500
b1100 7
1'
#730000
0'
#732500
b1101 7
1'
#735000
0'
#737500
b1110 7
1'
#740000
0'
#742500
b1111 7
1'
#745000
0'
#747500
b0 7
1'
#750000
0'
#752500
b1 7
1'
#755000
0'
#757500
b10 7
1'
#760000
0'
#762500
b11 7
1'
#765000
0'
#767500
b100 7
1'
#770000
0'
#772500
b101 7
1'
#775000
0'
#777500
b110 7
1'
#780000
0'
#782500
b111 7
1'
#785000
0'
#787500
b1000 7
1'
#790000
0'
#792500
b1001 7
1'
#795000
0'
#797500
b1010 7
1'
#800000
0'
#802500
b1011 7
1'
#805000
0'
#807500
b1100 7
1'
#810000
0'
#812500
b1101 7
1'
#815000
0'
#817500
b1110 7
1'
#820000
0'
#822500
b1111 7
b100 <
1'
b100 C
1)
#825000
0'
#827500
b0 7
1'
#830000
0'
#832500
b1 7
1'
#835000
0'
#837500
b10 7
1'
#840000
0'
#842500
b11 7
1'
#845000
0'
#847500
b100 7
1'
#850000
0'
#852500
b101 7
1'
#855000
0'
#857500
b110 7
1'
#860000
0'
#862500
b111 7
1'
#865000
0'
#867500
b1000 7
1'
#870000
0'
#872500
b1001 7
1'
#875000
0'
#877500
b1010 7
1'
#880000
0'
#882500
b1011 7
1'
#885000
0'
#887500
b1100 7
1'
#890000
0'
#892500
b1101 7
1'
#895000
0'
#897500
b1110 7
1'
#900000
0'
#902500
b1111 7
1'
#905000
0'
#907500
b0 7
1'
#910000
0'
#912500
b1 7
1'
#915000
0'
#917500
b10 7
1'
#920000
0'
#922500
b11 7
1'
1*
0)
#925000
0'
#927500
b100 7
1'
#930000
0'
#932500
b101 7
1'
#935000
0'
#937500
b110 7
1'
#940000
0'
#942500
b111 7
1'
#945000
0'
#947500
b1000 7
1'
#950000
0'
#952500
b1001 7
1'
#955000
0'
#957500
b1010 7
1'
#960000
0'
#962500
b1011 7
1'
#965000
0'
#967500
b1100 7
1'
#970000
0'
#972500
b1101 7
1'
#975000
0'
#977500
b1110 7
1'
#980000
0'
#982500
b1111 7
1'
#985000
0'
#987500
b0 7
1'
#990000
0'
#992500
b1 7
1'
#995000
0'
#997500
b10 7
1'
#1000000
0'
#1002500
b11 7
1'
#1005000
0'
#1007500
b100 7
1'
#1010000
0'
#1012500
b101 7
1'
#1015000
0'
#1017500
b110 7
1'
#1020000
0'
#1022500
b111 7
1A
b101 <
b10110 =
1'
b101 C
1)
#1025000
0'
#1027500
b1000 7
1'
#1030000
0'
#1032500
b1001 7
1'
#1035000
0'
#1037500
b1010 7
1'
#1040000
0'
#1042500
b1011 7
1'
#1045000
0'
#1047500
b1100 7
1'
#1050000
0'
#1052500
b1101 7
1'
#1055000
0'
#1057500
b1110 7
1'
#1060000
0'
#1062500
b1111 7
1'
#1065000
0'
#1067500
b0 7
1'
#1070000
0'
#1072500
b1 7
1'
#1075000
0'
#1077500
b10 7
1'
#1080000
0'
#1082500
b11 7
1'
#1085000
0'
#1087500
b100 7
1'
#1090000
0'
#1092500
b101 7
1'
#1095000
0'
#1097500
b110 7
1'
#1100000
0'
#1102500
b111 7
1'
#1105000
0'
#1107500
b1000 7
1'
#1110000
0'
#1112500
b1001 7
1'
#1115000
0'
#1117500
b1010 7
1'
#1120000
0'
#1122500
b1011 7
1'
#1125000
0'
#1127500
b1100 7
1'
#1130000
0'
#1132500
b1101 7
1'
#1135000
0'
#1137500
b1110 7
1'
#1140000
0'
#1142500
b1111 7
1'
#1145000
0'
#1147500
b0 7
1'
#1150000
0'
#1152500
b1 7
1'
#1155000
0'
#1157500
b10 7
1'
#1160000
0'
#1162500
b11 7
1'
#1165000
0'
#1167500
b100 7
1'
#1170000
0'
#1172500
b101 7
1'
#1175000
0'
#1177500
b110 7
1'
#1180000
0'
#1182500
b111 7
1'
#1185000
0'
#1187500
b1000 7
1'
#1190000
0'
#1192500
b1001 7
1'
#1195000
0'
#1197500
b1010 7
1'
#1200000
0'
#1202500
b1011 7
1'
#1205000
0'
#1207500
b1100 7
1'
#1210000
0'
#1212500
b1101 7
1'
#1215000
0'
#1217500
b1110 7
1'
#1220000
0'
#1222500
b1111 7
1'
#1225000
0'
#1227500
b0 7
1'
#1230000
0'
#1232500
b1 7
1'
#1235000
0'
#1237500
b10 7
1'
#1240000
0'
#1242500
b11 7
1'
#1245000
0'
#1247500
b100 7
1'
#1250000
0'
#1252500
b101 7
1'
#1255000
0'
#1257500
b110 7
1'
#1260000
0'
#1262500
b111 7
1'
#1265000
0'
#1267500
b1000 7
1'
